astrosr/__init__.py
astrosr/__main__.py
astrosr/cli.py
astrosr/drizzle_super_resolution.py
astrosr-1.0.4.dist-info/LICENSE
astrosr-1.0.4.dist-info/METADATA
astrosr-1.0.4.dist-info/WHEEL
astrosr-1.0.4.dist-info/entry_points.txt
astrosr-1.0.4.dist-info/top_level.txt
astrosr-1.0.4.dist-info/RECORD
