Metadata-Version: 2.1
Name: astrosr
Version: 1.0.4
Summary: Astronomical super-resolution with drizzle for wide field-of-view images
Author-email: Elías Gabriel Ferrer Jorge <gabrielferrerjorge@gmail.com>
Maintainer-email: Elías Gabriel Ferrer Jorge <gabrielferrerjorge@gmail.com>
License: MIT License
Project-URL: Homepage, https://github.com/dot-gabriel-ferrer/astroSR
Project-URL: Documentation, https://github.com/dot-gabriel-ferrer/astroSR#readme
Project-URL: Repository, https://github.com/dot-gabriel-ferrer/astroSR
Project-URL: Bug Tracker, https://github.com/dot-gabriel-ferrer/astroSR/issues
Project-URL: Changelog, https://github.com/dot-gabriel-ferrer/astroSR/blob/main/CHANGELOG.md
Keywords: astronomy,astrophysics,drizzle,super-resolution,fits,wcs,image-processing,scientific-computing
Classifier: Development Status :: 5 - Production/Stable
Classifier: Intended Audience :: Science/Research
Classifier: Operating System :: OS Independent
Classifier: Programming Language :: Python :: 3
Classifier: Programming Language :: Python :: 3.9
Classifier: Programming Language :: Python :: 3.10
Classifier: Programming Language :: Python :: 3.11
Classifier: Programming Language :: Python :: 3.12
Classifier: Topic :: Scientific/Engineering :: Astronomy
Classifier: Topic :: Scientific/Engineering :: Image Processing
Classifier: Topic :: Software Development :: Libraries :: Python Modules
Requires-Python: >=3.9
License-File: LICENSE
Requires-Dist: numpy<2.0,>=1.20.0
Requires-Dist: astropy>=6.0
Requires-Dist: matplotlib>=3.5.0
Requires-Dist: drizzlepac>=3.6.0
Requires-Dist: scipy>=1.7.0
Requires-Dist: numba>=0.56.0
Requires-Dist: tqdm>=4.62.0
Requires-Dist: pandas>=1.3.0
Provides-Extra: all
Requires-Dist: astrosr[dev,docs,test]; extra == "all"
Provides-Extra: dev
Requires-Dist: black>=22.0.0; extra == "dev"
Requires-Dist: flake8>=5.0.0; extra == "dev"
Requires-Dist: isort>=5.10.0; extra == "dev"
Requires-Dist: mypy>=0.991; extra == "dev"
Requires-Dist: pre-commit>=2.20.0; extra == "dev"
Provides-Extra: docs
Requires-Dist: sphinx>=5.0.0; extra == "docs"
Requires-Dist: sphinx-rtd-theme>=1.0.0; extra == "docs"
Requires-Dist: myst-parser>=0.18.0; extra == "docs"
Provides-Extra: test
Requires-Dist: pytest>=7.0.0; extra == "test"
Requires-Dist: pytest-cov>=4.0.0; extra == "test"
Requires-Dist: pytest-xvfb>=2.0.0; extra == "test"
